brink/__init__.py
brink/application.py
brink/config.py
brink/db.py
brink/decorators.py
brink/exceptions.py
brink/fields.py
brink/handlers.py
brink/middleware.py
brink/models.py
brink/object_manager.py
brink/old_models.py
brink/serialization.py
brink/server.py
brink/urls.py
brink/utils.py
brink/cli/__init__.py
brink/cli/emojis.py
brink-0.3.0.data/scripts/brink
brink-0.3.0.dist-info/DESCRIPTION.rst
brink-0.3.0.dist-info/METADATA
brink-0.3.0.dist-info/RECORD
brink-0.3.0.dist-info/WHEEL
brink-0.3.0.dist-info/metadata.json
brink-0.3.0.dist-info/top_level.txt
