Metadata-Version: 2.0
Name: brink
Version: 0.3.0
Summary: A simple real time web framework based on            aiohttp and RethinkDB.
Home-page: https://github.com/lohmander/brink
Author: CH Lohmander
Author-email: hannes@lohmander.me
License: BSD-3
Keywords: sample setuptools development
Platform: UNKNOWN
Classifier: Development Status :: 3 - Alpha
Classifier: Intended Audience :: Developers
Classifier: Topic :: Software Development :: Build Tools
Classifier: License :: OSI Approved :: BSD License
Classifier: Programming Language :: Python :: 3.6
Requires-Dist: aiohttp
Requires-Dist: aiohttp-autoreload
Requires-Dist: inflection
Requires-Dist: pycolor
Requires-Dist: rethinkdb
Provides-Extra: dev
Requires-Dist: check-manifest; extra == 'dev'
Provides-Extra: test
Requires-Dist: coverage; extra == 'test'
